gen3rftools/__init__.py
gen3rftools/common/__init__.py
gen3rftools/common/tools.py
gen3rftools/scpi/__init__.py
gen3rftools/scpi/fsw.py
gen3rftools/soap/__init__.py
gen3rftools/soap/soapmessage.py
gen3rftools/soap/soaptalker.py
gen3rftools/soap/soaptalker_gui.py
gen3rftools/system/__init__.py
gen3rftools/system/windows.py
gen3rftools/transport/__init__.py
gen3rftools/transport/_ssh.py
gen3rftools/transport/sftp.py
gen3rftools/transport/ssh.py
gen3rftools/transport/visa.py
gen3rftools-0.30.dist-info/LICENSE
gen3rftools-0.30.dist-info/METADATA
gen3rftools-0.30.dist-info/WHEEL
gen3rftools-0.30.dist-info/top_level.txt
gen3rftools-0.30.dist-info/RECORD
