Metadata-Version: 2.1
Name: gen3rftools
Version: 0.30
Summary: UNKNOWN
Home-page: https://github.com/falomsc/gen3rftools
Author: falomsc
Author-email: falomsc@gmail.com
License: MIT
Platform: UNKNOWN
Requires-Python: >=3.4, <4
License-File: LICENSE
Requires-Dist: paramiko
Requires-Dist: pyvisa
Requires-Dist: pywinauto
Requires-Dist: goto-statement
Requires-Dist: goto-label
Requires-Dist: pyqt6
Requires-Dist: pywin32
